Workbook

Sheet Projects_Details
A1: S. No. | B1: PI Name | C1: Co-PI Name | D1: Department | E1: Project Title | F1: Funding Agency | G1: Sanctioned Amount (INR) | H1: Duration (Years) | I1: Sanctioned Year | J1: CAY (CAYm1/CAYm2/CAYm3)
A2: 1 | B2: Prof. A | C2: Dr. B | D2: ECE | E2: IoT for Smart Health | F2: DST | G2: 2200000 | H2: 3 | I2: 2023 | J2: CAYm1
A3: 2 | B3: Dr. C | D3: CSE | E3: AI in Agriculture | F3: Infosys CSR | G3: 1850000 | H3: 2 | I3: 2022 | J3: CAYm2
A4: 3 | B4: Prof. D | C4: Dr. E | D4: ME | E4: Sustainable Energy | F4: UGC | G4: 900000 | H4: 2 | I4: 2021 | J4: CAYm3

Sheet Yearly_Summary
A1: Academic Year | B1: Total Funding (INR) | C1: No. of Projects | D1: Highest Value Project (INR) | E1: NBA Marks (Auto)
A2: CAYm1 | B2: =SUMIF(Projects_Details!J2:J500,"CAYm1",Projects_Details!G2:G500) | C2: =COUNTIF(Projects_Details!J2:J500,"CAYm1") | D2: =IF(C2=0,0,MAXIFS(Projects_Details!G2:G500,Projects_Details!J2:J500,"CAYm1")) | E2: =IF(B2>2000000,15, IF(B2>1600000,12, IF(B2>1200000,9, IF(B2>800000,6, IF(B2>400000,3, IF(B2>100000,1,0))))))
A3: CAYm2 | B3: =SUMIF(Projects_Details!J2:J500,"CAYm2",Projects_Details!G2:G500) | C3: =COUNTIF(Projects_Details!J2:J500,"CAYm2") | D3: =IF(C3=0,0,MAXIFS(Projects_Details!G2:G500,Projects_Details!J2:J500,"CAYm2")) | E3: =IF(B3>2000000,15, IF(B3>1600000,12, IF(B3>1200000,9, IF(B3>800000,6, IF(B3>400000,3, IF(B3>100000,1,0))))))
A4: CAYm3 | B4: =SUMIF(Projects_Details!J2:J500,"CAYm3",Projects_Details!G2:G500) | C4: =COUNTIF(Projects_Details!J2:J500,"CAYm3") | D4: =IF(C4=0,0,MAXIFS(Projects_Details!G2:G500,Projects_Details!J2:J500,"CAYm3")) | E4: =IF(B4>2000000,15, IF(B4>1600000,12, IF(B4>1200000,9, IF(B4>800000,6, IF(B4>400000,3, IF(B4>100000,1,0))))))
A5: Cumulative | B5: =SUM(B2:B4) | C5: =SUM(C2:C4) | D5: =MAX(D2:D4) | E5: =IF(B5>2000000,15, IF(B5>1600000,12, IF(B5>1200000,9, IF(B5>800000,6, IF(B5>400000,3, IF(B5>100000,1,0))))))

Sheet Marks_Calculator
A1: Description | B1: Amount (INR) | C1: NBA Marks (Auto)
A2: Enter cumulative sanctioned amount here | C2: =IF(B2>2000000,15, IF(B2>1600000,12, IF(B2>1200000,9, IF(B2>800000,6, IF(B2>400000,3, IF(B2>100000,1,0))))))
A3: Note: | B3: Thresholds (INR): >20L=15, >16L=12, >12L=9, >8L=6, >4L=3, >1L=1, else=0

Sheet Evidence_Tracker
A1: Project Title | B1: Funding Agency | C1: Sanction Letter (Link/Ref No.) | D1: Utilization Certificate (Y/N) | E1: MoU/Agreement (Y/N) | F1: Progress/Final Report (Y/N) | G1: Remarks
A2: IoT for Smart Health | B2: DST | C2: Doc123.pdf | D2: Yes | E2: Yes | F2: Yes | G2: Completed
A3: AI in Agriculture | B3: Infosys CSR | C3: Doc456.pdf | D3: Yes | E3: Yes | F3: Ongoing | G3: Mid-term report submitted
A4: Sustainable Energy | B4: UGC | C4: Doc789.pdf | D4: Yes | F4: Yes | G4: Completed

Sheet ReadMe
A1: How to use this template:
A2: 1) Fill 'Projects_Details' with one row per sponsored research project. Use the dropdown in column J to select CAYm1/CAYm2/CAYm3.
A3: 2) 'Yearly_Summary' auto-calculates Year-wise totals, counts, highest-value project, and NBA marks.
A4: 3) 'Marks_Calculator' lets you manually test marks for any cumulative amount you enter in cell B2.
A5: 4) 'Evidence_Tracker' helps you keep links/refs to sanction letters, UCs, MoUs, and reports for NBA verification.
A6: Notes: Amount thresholds are in INR (1 Lakh = 100,000). Ensure sanctioned amounts exclude consultancy or in-house R&D to avoid duplication with 6.2.5 and 6.2.6.

Sheet MoU_CSR_Tracker
A1: Project Title | B1: Industry/CSR Partner | C1: MoU/Agreement Ref. No. | D1: Date Signed | E1: Funding Amount (Lakhs) | F1: Duration (Years) | G1: Link to Copy (PDF/Doc) | H1: Remarks
A2: AI in Agriculture | B2: Infosys CSR | C2: MoU-CSR-2022-01 | D2: 2022-06-15 | E2: 18.5 | F2: 2 | G2: MoU_AI_Agri.pdf | H2: Ongoing
A3: Green Energy Research | B3: Reliance Foundation | C3: MoU-CSR-2021-05 | D3: 2021-09-10 | E3: 12 | F3: 3 | G3: MoU_GreenEnergy.pdf | H3: Prototype Developed

Sheet UC_Tracker
A1: Project Title | B1: Funding Agency | C1: UC Reference No. | D1: Period Covered | E1: Amount Utilized (₹) | F1: Date of Submission | G1: Verified By (Head/Finance Officer) | H1: Link to UC (PDF/Doc) | I1: Remarks
A2: IoT for Smart Health | B2: DST | C2: UC-DST-2023-01 | D2: 2022-23 | E2: 1200000 | F2: 2023-03-31 | G2: Finance Officer | H2: UC_IoT_DST.pdf | I2: Acknowledged by DST
A3: AI in Agriculture | B3: Infosys CSR | C3: UC-CSR-2022-04 | D3: 2021-22 | E3: 1000000 | F3: 2022-03-20 | G3: Director | H3: UC_AI_CSR.pdf | I3: Second installment released

Sheet Financial_Evidence_Tracker
A1: Project Title | B1: Funding Agency | C1: Amount Sanctioned (₹ Lakhs) | D1: Amount Received (₹ Lakhs) | E1: Amount Utilized (₹ Lakhs) | F1: Bank Statement Ref/Date | G1: Audit Report Ref/Date | H1: Link to Document (PDF/Doc) | I1: Remarks
A2: IoT for Smart Health | B2: DST | C2: 22 | D2: 22 | E2: 21.5 | F2: BankStmt_DST_2023.pdf | G2: Audit_DST_2023.pdf | H2: Link_DST_Fin.pdf | I2: Utilized fully, minor balance carried forward
A3: AI in Agriculture | B3: Infosys CSR | C3: 18.5 | D3: 18.5 | E3: 18 | F3: BankStmt_CSR_2022.pdf | G3: Audit_CSR_2022.pdf | H3: Link_CSR_Fin.pdf | I3: Second installment pending at audit time

Sheet RD_Tracker
A1: S. No. | B1: PI Name | C1: Co-PI Name | D1: Department | E1: Project Title | F1: Funding Type (Seed/Internal) | G1: Sanctioned Amount (₹ Lakhs) | H1: Duration | I1: Sanctioned Year | J1: CAY (CAYm1/CAYm2/CAYm3) | K1: Amount Released (₹) | L1: Amount Utilized (₹)
A2: 1 | B2: Prof. X | D2: CSE | E2: Dept. Seed Grant on Edge AI | F2: Seed | G2: 3 | H2: 1 year | I2: 2023 | J2: CAYm1 | K2: 300000 | L2: 250000
A3: 2 | B3: Dr. Y | C3: Dr. Z | D3: EEE | E3: Prototype Fund - Smart Inverter | F3: Internal | G3: 2 | H3: 1 year | I3: 2022 | J3: CAYm2 | K3: 200000 | L3: 180000

Sheet NBA_Marks_Dashboard
A1: NBA Marks Dashboard – Consolidated View (Sponsored Research + Consultancy + R&D)
A3: Category | B3: CAYm1 Total (₹) | C3: CAYm2 Total (₹) | D3: CAYm3 Total (₹) | E3: Cumulative (₹) | F3: NBA Marks (Auto) | G3: Notes
A4: Sponsored Research | B4: =IFERROR(Yearly_Summary!B2, SUMIF(Projects_Details!J2:J500,"CAYm1",Projects_Details!G2:G500)) | C4: =IFERROR(Yearly_Summary!B3, SUMIF(Projects_Details!J2:J500,"CAYm2",Projects_Details!G2:G500)) | D4: =IFERROR(Yearly_Summary!B4, SUMIF(Projects_Details!J2:J500,"CAYm3",Projects_Details!G2:G500)) | E4: =SUM(B4:D4) | F4: =IF(E4>2000000,15,IF(E4>1600000,12,IF(E4>1200000,9,IF(E4>800000,6,IF(E4>400000,3,IF(E4>100000,1,0)))))) | G4: Externally funded research only (exclude consultancy & in-house R&D)
A5: Consultancy | B5: =SUMIF(Consultancy_Tracker!J2:J500,"CAYm1",Consultancy_Tracker!K2:K500) | C5: =SUMIF(Consultancy_Tracker!J2:J500,"CAYm2",Consultancy_Tracker!K2:K500) | D5: =SUMIF(Consultancy_Tracker!J2:J500,"CAYm3",Consultancy_Tracker!K2:K500) | E5: =SUM(B5:D5) | F5: =IF(E5>2000000,15,IF(E5>1600000,12,IF(E5>1200000,9,IF(E5>800000,6,IF(E5>400000,3,IF(E5>100000,1,0)))))) | G5: Exclude funded research & in-house R&D (no duplication with 6.2.4/6.2.6)
A6: R&D / Seed Money (Internal) | B6: =SUMIF(RD_Tracker!J2:J500,"CAYm1",RD_Tracker!K2:K500) | C6: =SUMIF(RD_Tracker!J2:J500,"CAYm2",RD_Tracker!K2:K500) | D6: =SUMIF(RD_Tracker!J2:J500,"CAYm3",RD_Tracker!K2:K500) | E6: =SUM(B6:D6) | F6: — | G6: Internal funding; scored under a different sub-criterion (6.2.6).
A8: Grand Total (Sponsored + Consultancy + R&D) | B8: =SUM(B4:B6) | C8: =SUM(C4:C6) | D8: =SUM(D4:D6) | E8: =SUM(E4:E6)
A10: Notes:
A11: 1) Sponsored Research and Consultancy are each scored out of 15 marks based on cumulative receipts over CAYm1–CAYm3.
A12: 2) R&D/Seed Money (internal) is shown for completeness but is evaluated under a separate NBA sub-criterion (6.2.6).
A13: 3) Ensure no duplication across categories; a project must appear in only one bucket.
A14: 4) Amount thresholds assume INR; 1 Lakh = 100,000.

Sheet Consultancy_Tracker
A1: S. No. | B1: PI Name | C1: Co-PI Name | D1: Department | E1: Project Title | F1: Client/Funding Agency | G1: Agency Type | H1: Sanctioned Amount (₹ Lakhs) | I1: Duration | J1: Sanctioned Year | K1: CAYm1 Amount Received (₹) | L1: CAYm1 Amount Received (₹) | M1: CAYm2 Amount Received (₹) | N1: CAYm3 Amount Received (₹) | O1: Total Amount Received (₹) | P1: Total Amount (₹ Lakhs) | Q1: CAYm2 Amount Received (₹) | R1: CAYm3 Amount Received (₹) | S1: Total Amount Received (₹ Lakhs)
A2: 1 | B2: Prof. A | C2: Dr. B | D2: Civil | E2: Structural Audit of XYZ | F2: XYZ Constructions Pvt. Ltd. | G2: Industry | H2: 5 | I2: 1 year | J2: 2023 | K2: 300000 | O2: =SUM(K2:M2) | P2: =N2/100000 | Q2: 200000 | R2: 0 | S2: =ROUND(SUM(J2:L2)/100000,2)
A3: 2 | B3: Dr. C | D3: Mechanical | E3: Material Testing for ABC | F3: ABC Industries | G3: Industry | H3: 3.5 | I3: 6 months | J3: 2022 | K3: 0 | O3: =SUM(K3:M3) | P3: =N3/100000 | Q3: 250000 | R3: 100000 | S3: =ROUND(SUM(J3:L3)/100000,2)
A4: 3 | B4: Prof. D | C4: Dr. E | D4: IT | E4: Software Audit for PQR Ltd. | F4: PQR Ltd. | G4: Industry | H4: 12 | I4: 1.5 years | J4: 2021 | K4: 600000 | O4: =SUM(K4:M4) | P4: =N4/100000 | Q4: 400000 | R4: 200000 | S4: =ROUND(SUM(J4:L4)/100000,2)
A5: Summary (Consultancy Revenue) | O5: =SUM(K5:M5) | P5: =N5/100000
A6: Academic Year | B6: Total Consultancy Revenue (₹) | C6: NBA Marks (Auto) | O6: =SUM(K6:M6) | P6: =N6/100000
A7: CAYm1 | B7: =SUM(K2:K500) | C7: =IF(B7>2000000,15, IF(B7>1600000,12, IF(B7>1200000,9, IF(B7>800000,6, IF(B7>400000,3, IF(B7>100000,1,0)))))) | O7: =SUM(K7:M7) | P7: =N7/100000
A8: CAYm2 | B8: =SUM(L2:L500) | C8: =IF(B8>2000000,15, IF(B8>1600000,12, IF(B8>1200000,9, IF(B8>800000,6, IF(B8>400000,3, IF(B8>100000,1,0)))))) | O8: =SUM(K8:M8) | P8: =N8/100000
A9: CAYm3 | B9: =SUM(M2:M500) | C9: =IF(B9>2000000,15, IF(B9>1600000,12, IF(B9>1200000,9, IF(B9>800000,6, IF(B9>400000,3, IF(B9>100000,1,0)))))) | O9: =SUM(K9:M9) | P9: =N9/100000
A10: Cumulative | B10: =SUM(B7:B9) | C10: =IF(B10>2000000,15, IF(B10>1600000,12, IF(B10>1200000,9, IF(B10>800000,6, IF(B10>400000,3, IF(B10>100000,1,0)))))) | O10: =SUM(K10:M10) | P10: =N10/100000
O11: =SUM(K11:M11) | P11: =N11/100000
O12: =SUM(K12:M12) | P12: =N12/100000
O13: =SUM(K13:M13) | P13: =N13/100000
O14: =SUM(K14:M14) | P14: =N14/100000
O15: =SUM(K15:M15) | P15: =N15/100000
O16: =SUM(K16:M16) | P16: =N16/100000
O17: =SUM(K17:M17) | P17: =N17/100000
O18: =SUM(K18:M18) | P18: =N18/100000
O19: =SUM(K19:M19) | P19: =N19/100000
O20: =SUM(K20:M20) | P20: =N20/100000
O21: =SUM(K21:M21) | P21: =N21/100000
O22: =SUM(K22:M22) | P22: =N22/100000
... O500: =SUM(K500:M500) | P500: =N500/100000

Sheet Faculty_Consultancy_Report
A1: PI Name | B1: CAYm1 Consultancy Revenue (₹) | C1: CAYm2 Consultancy Revenue (₹) | D1: CAYm3 Consultancy Revenue (₹) | E1: Total Consultancy Revenue (₹) | F1: Total Consultancy Revenue (₹ Lakhs)
A2: Prof. A | B2: 0 | C2: 200000 | D2: 0 | E2: 200000 | F2: 2
A3: Dr. C | B3: 0 | C3: 250000 | D3: 100000 | E3: 350000 | F3: 3.5
A4: Prof. D | B4: 0 | C4: 400000 | D4: 200000 | E4: 600000 | F4: 6
A5: Total Consultancy Revenue (₹) | B5: 0 | C5: 0 | D5: 0 | E5: 0 | F5: 0
A6: =SUM(K2:K500) | B6: 0 | C6: 0 | D6: 0 | E6: 0 | F6: 0
A7: =SUM(L2:L500) | B7: 0 | C7: 0 | D7: 0 | E7: 0 | F7: 0
A8: =SUM(M2:M500) | B8: 0 | C8: 0 | D8: 0 | E8: 0 | F8: 0
A9: =SUM(B7:B9) | B9: 0 | C9: 0 | D9: 0 | E9: 0 | F9: 0

Sheet Consultancy_Title_Repository
A1: S. No. | B1: Project Title | C1: Department | D1: PI Name | E1: Client/Funding Agency | F1: Sanctioned Year | G1: Tags / Keywords (Testing, Audit, Training, Prototype, Software, etc.) | H1: Remarks
A2: 1 | B2: Structural Audit of XYZ Commercial Complex | C2: Civil Engg | D2: Prof. A | E2: XYZ Constructions Pvt. Ltd. | F2: 2023 | G2: Structural Audit, Safety, Civil | H2: Completed
A3: 2 | B3: Material Testing and Failure Analysis for Automotive Components | C3: Mechanical Engg | D3: Dr. C | E3: ABC Industries | F3: 2022 | G3: Testing, Materials, Automotive | H3: Ongoing
A4: 3 | B4: Cybersecurity Penetration Testing for PQR Ltd. | C4: CSE | D4: Prof. D | E4: PQR Ltd. | F4: 2021 | G4: Cybersecurity, Software Audit, IT | H4: Completed
A5: 4 | B5: Energy Audit and Efficiency Recommendations for DEF Manufacturing Unit | C5: Mechanical Engg | D5: Dr. E | E5: DEF Manufacturing Ltd. | F5: 2023 | G5: Energy Audit, Efficiency, Mechanical | H5: Report Submitted

Sheet Institution_SeedMoney_Tracker
A1: S. No. | B1: Faculty Name (PI) | C1: Department | D1: Project Title | E1: Support for Activity | F1: Duration (Months) | G1: Sanctioned Amount (₹ Lakhs) | H1: Utilized Amount (₹ Lakhs) | I1: CAYm1 Amount Received (₹) | J1: CAYm2 Amount Received (₹) | K1: CAYm3 Amount Received (₹) | L1: Total Amount Received (₹) | M1: Total Amount Received (₹ Lakhs) | N1: Sanctioned Year | O1: CAY (CAYm1/CAYm2/CAYm3) | P1: Publications (Count) | Q1: Prototypes (Count) | R1: Ph.D. Graduated (Count) | S1: M.E./M.Tech. Graduated (Count) | T1: Revenue Generated Later (₹) | U1: Remarks | V1: Outcomes (Summary)
A2: 1 | B2: Prof. Alpha | C2: CSE | D2: Seed: Lightweight CNN for Edge Devices | G2: 3 | H2: 2.8 | L2: =SUM(I2:K2) | M2: =L2/100000 | N2: 2023 | O2: CAYm1 | P2: 2 | Q2: 1 | R2: 0 | S2: 1 | T2: 50000 | U2: On time
A3: 2 | B3: Dr. Beta | C3: ECE | D3: Seed: IoT Health Monitor Prototype | G3: 2.5 | H3: 2.5 | L3: =SUM(I3:K3) | M3: =L3/100000 | N3: 2022 | O3: CAYm2 | P3: 1 | Q3: 1 | R3: 0 | S3: 2 | U3: Completed
A4: 3 | B4: Prof. Gamma | C4: ME | D4: Seed: Micro Wind Turbine Prototype | G4: 1.2 | H4: 1 | L4: =SUM(I4:K4) | M4: =L4/100000 | N4: 2021 | O4: CAYm3 | P4: 0 | Q4: 1 | R4: 0 | S4: 0 | U4: Ongoing paper under review
L5: =SUM(I5:K5) | M5: =L5/100000
L6: =SUM(I6:K6) | M6: =L6/100000
L7: =SUM(I7:K7) | M7: =L7/100000
L8: =SUM(I8:K8) | M8: =L8/100000
L9: =SUM(I9:K9) | M9: =L9/100000
L10: =SUM(I10:K10) | M10: =L10/100000
L11: =SUM(I11:K11) | M11: =L11/100000
L12: =SUM(I12:K12) | M12: =L12/100000
L13: =SUM(I13:K13) | M13: =L13/100000
L14: =SUM(I14:K14) | M14: =L14/100000
L15: =SUM(I15:K15) | M15: =L15/100000
L16: =SUM(I16:K16) | M16: =L16/100000
... L500: =SUM(I500:K500) | M500: =L500/100000
A505: Summary – Institution Seed Money (Internal Research Grants)
A506: Academic Year | B506: Sanctioned Total (₹ Lakhs) | C506: Utilized Total (₹ Lakhs) | D506: Received Total (₹ Lakhs)
A507: CAYm1 | B507: =SUMIF(H2:H500,"CAYm1",E2:E500) | C507: =SUMIF(H2:H500,"CAYm1",F2:F500) | D507: =SUM(I2:I500)/100000
A508: CAYm2 | B508: =SUMIF(H2:H500,"CAYm2",E2:E500) | C508: =SUMIF(H2:H500,"CAYm2",F2:F500) | D508: =SUM(J2:J500)/100000
A509: CAYm3 | B509: =SUMIF(H2:H500,"CAYm3",E2:E500) | C509: =SUMIF(H2:H500,"CAYm3",F2:F500) | D509: =SUM(K2:K500)/100000
A510: Total | B510: =SUM(B507:B509) | C510: =SUM(C507:C509) | D510: =SUM(D507:D509)
A512: Marks – Received (3) + Utilized (2)
A513: Received Marks (3) | B513: =IF(D510>6,3,IF(D510>4,2,IF(D510>2,1,0)))
A514: Utilized Marks (2) | B514: =IF(B510=0,0,MIN(2,2*(C510/B510)))
A515: Total Marks (out of 5) | B515: =B513+B514
A517: Notes: 1) Amounts are in ₹ Lakhs. 2) Received marks follow NBA thresholds; Utilized marks scale with utilization ratio (100% ⇒ 2). 3) Avoid duplication with 6.2.4/6.2.5.

Sheet SeedMoney_Tracker
A1: S. No. | B1: Faculty Name (PI) | C1: Department | D1: Project Title | E1: Support for Activity | F1: Duration (Months) | G1: Sanctioned Amount (₹ Lakhs) | H1: Utilized Amount (₹ Lakhs) | I1: Sanctioned Year | J1: CAY (CAYm1/CAYm2/CAYm3) | K1: Publications (No.) | L1: Prototypes (No.) | M1: Ph.D. Graduated (No.) | N1: M.E./M.Tech. Graduated (No.) | O1: Revenue Generated (₹) | P1: Outcome Type | Q1: DOI/Patent/Thesis ID | R1: Outcome Link (PDF/URL) | S1: Outcomes (Summary) | T1: CAYm1 Amount Received (₹) | U1: CAYm2 Amount Received (₹) | V1: CAYm3 Amount Received (₹) | W1: Total Amount Received (₹) | X1: Total Amount Received (₹ Lakhs)
A2: 1 | B2: Prof. Alpha | C2: CSE | D2: AI-based Crop Prediction | E2: Prototype Development | F2: 6 | G2: 3 | H2: 2.8 | I2: 2023 | J2: CAYm1 | K2: 2 | L2: 1 | M2: 0 | N2: 1 | O2: 50000 | P2: Publication | Q2: 10.1016/j.xxx.2024.001 | R2: https://doi.org/10.1016/j.xxx.2024.001 | S2: 2 Scopus papers; 1 prototype (TRL-4); 1 M.Tech | T2: 180000 | U2: 100000 | W2: =SUM(T2:V2) | X2: =W2/100000
A3: 2 | B3: Dr. Beta | C3: ECE | D3: IoT for Smart Health | E3: Lab Setup & Validation | F3: 8 | G3: 2.5 | H3: 2.5 | I3: 2022 | J3: CAYm2 | K3: 1 | L3: 1 | M3: 0 | N3: 2 | P3: Prototype | S3: 1 paper; 1 prototype; 2 M.Tech | U3: 150000 | V3: 100000 | W3: =SUM(T3:V3) | X3: =W3/100000
A4: 3 | B4: Prof. Gamma | C4: ME | D4: Micro Wind Turbine Prototype | E4: Design & Fabrication | F4: 10 | G4: 1.2 | H4: 1 | I4: 2021 | J4: CAYm3 | K4: 0 | L4: 1 | M4: 0 | N4: 0 | P4: Dissertation-ME/MTech | S4: 1 prototype; thesis under review | V4: 100000 | W4: =SUM(T4:V4) | X4: =W4/100000
W5: =SUM(T5:V5) | X5: =W5/100000
W6: =SUM(T6:V6) | X6: =W6/100000
W7: =SUM(T7:V7) | X7: =W7/100000
W8: =SUM(T8:V8) | X8: =W8/100000
W9: =SUM(T9:V9) | X9: =W9/100000
W10: =SUM(T10:V10) | X10: =W10/100000
W11: =SUM(T11:V11) | X11: =W11/100000
W12: =SUM(T12:V12) | X12: =W12/100000
W13: =SUM(T13:V13) | X13: =W13/100000
W14: =SUM(T14:V14) | X14: =W14/100000
W15: =SUM(T15:V15) | X15: =W15/100000
W16: =SUM(T16:V16) | X16: =W16/100000
... W1000: =SUM(T1000:V1000) | X1000: =W1000/100000

Sheet Seed_Summary
A1: Institution Seed Money – Year-wise Summary & Marks
A2: Academic Year | B2: Sanctioned Total (₹ Lakhs) | C2: Utilized Total (₹ Lakhs) | D2: Received Total (₹ Lakhs) | E2: Publications (No.) | F2: Prototypes (No.) | G2: Ph.D. Graduated (No.) | H2: M.E./M.Tech. Graduated (No.)
A3: CAYm1 | B3: =SUMIF(SeedMoney_Tracker!J2:J1000,"CAYm1",SeedMoney_Tracker!G2:G1000) | C3: =SUMIF(SeedMoney_Tracker!J2:J1000,"CAYm1",SeedMoney_Tracker!H2:H1000) | D3: =SUM(SeedMoney_Tracker!T2:T1000)/100000 | E3: =SUMIF(SeedMoney_Tracker!J2:J1000,"CAYm1",SeedMoney_Tracker!K2:K1000) | F3: =SUMIF(SeedMoney_Tracker!J2:J1000,"CAYm1",SeedMoney_Tracker!L2:L1000) | G3: =SUMIF(SeedMoney_Tracker!J2:J1000,"CAYm1",SeedMoney_Tracker!M2:M1000) | H3: =SUMIF(SeedMoney_Tracker!J2:J1000,"CAYm1",SeedMoney_Tracker!N2:N1000)
A4: CAYm2 | B4: =SUMIF(SeedMoney_Tracker!J2:J1000,"CAYm2",SeedMoney_Tracker!G2:G1000) | C4: =SUMIF(SeedMoney_Tracker!J2:J1000,"CAYm2",SeedMoney_Tracker!H2:H1000) | D4: =SUM(SeedMoney_Tracker!U2:U1000)/100000 | E4: =SUMIF(SeedMoney_Tracker!J2:J1000,"CAYm2",SeedMoney_Tracker!K2:K1000) | F4: =SUMIF(SeedMoney_Tracker!J2:J1000,"CAYm2",SeedMoney_Tracker!L2:L1000) | G4: =SUMIF(SeedMoney_Tracker!J2:J1000,"CAYm2",SeedMoney_Tracker!M2:M1000) | H4: =SUMIF(SeedMoney_Tracker!J2:J1000,"CAYm2",SeedMoney_Tracker!N2:N1000)
A5: CAYm3 | B5: =SUMIF(SeedMoney_Tracker!J2:J1000,"CAYm3",SeedMoney_Tracker!G2:G1000) | C5: =SUMIF(SeedMoney_Tracker!J2:J1000,"CAYm3",SeedMoney_Tracker!H2:H1000) | D5: =SUM(SeedMoney_Tracker!V2:V1000)/100000 | E5: =SUMIF(SeedMoney_Tracker!J2:J1000,"CAYm3",SeedMoney_Tracker!K2:K1000) | F5: =SUMIF(SeedMoney_Tracker!J2:J1000,"CAYm3",SeedMoney_Tracker!L2:L1000) | G5: =SUMIF(SeedMoney_Tracker!J2:J1000,"CAYm3",SeedMoney_Tracker!M2:M1000) | H5: =SUMIF(SeedMoney_Tracker!J2:J1000,"CAYm3",SeedMoney_Tracker!N2:N1000)
A6: Total | B6: =SUM(B3:B5) | C6: =SUM(C3:C5) | D6: =SUM(D3:D5) | E6: =SUM(E3:E5) | F6: =SUM(F3:F5) | G6: =SUM(G3:G5) | H6: =SUM(H3:H5)
A9: Marks – Received (3) + Utilized (2)
A10: Received Marks (3) | B10: =IF(D6>=6,3,IF(D6>=4,2,IF(D6>=2,1,0)))
A11: Utilized Marks (2) | B11: =IF(B6=0,0,MIN(2,2*(C6/B6)))
A12: Total Marks (out of 5) | B12: =B10+B11

Sheet Seed_ReadMe
A1: How to use this file (Institution Seed Money / Internal Research Grants)
A3: 1) Enter one row per seed-money project in SeedMoney_Tracker. Use dropdowns for CAY and Outcome Type.
A4: 2) Enter Sanctioned/Utilized amounts in Lakhs; year-wise receipts in ₹ per CAY (columns T–V).
A5: 3) Summary sheet auto-computes CAY-wise totals, outcomes, and NBA marks (Received 3 + Utilized 2).
A6: 4) Add hyperlinks to outcome PDFs/DOIs in 'Outcome Link (PDF/URL)' and a crisp line in 'Outcomes (Summary)'.
A7: 5) Avoid duplication with Sponsored (6.2.4) and Consultancy (6.2.5). Keep sanction orders, UCs, invoices handy.

Sheet Academic_Research
A1: S. No. | B1: Department | C1: PI/Author(s) | D1: Publication Title | E1: Venue (Journal/Conf.) | F1: DOI/URL | G1: Indexing (Scopus/WoS/CARE) | H1: Year | I1: CAY (CAYm1/CAYm2/CAYm3) | J1: Acknowledges Funding? (Y/N)
A1005: Academic Research – CAY-wise Counts
A1006: Academic Year | B1006: Publications (Count)
A1007: CAYm1 | B1007: =COUNTIF(I2:I1000,"CAYm1")
A1008: CAYm2 | B1008: =COUNTIF(I2:I1000,"CAYm2")
A1009: CAYm3 | B1009: =COUNTIF(I2:I1000,"CAYm3")
A1010: Total | B1010: =SUM(B1007:B1009)

Sheet PhD_Students
A1: S. No. | B1: Student Name | C1: Registration No. | D1: Department | E1: Thesis Title/Area | F1: Supervisor (PI)/Co-supervisor | G1: Status (Ongoing/Awarded) | H1: Award/Regn Year | I1: CAY (CAYm1/CAYm2/CAYm3) | J1: Publications (Count) | K1: Funding Source (TA/RA/Project) | L1: Thesis Link/ID
A1005: Ph.D. – CAY-wise Summary
A1006: Academic Year | B1006: Awarded (Count) | C1006: Ongoing (Count)
A1007: CAYm1 | B1007: =COUNTIFS(I2:I1000,"CAYm1",G2:G1000,"Awarded") | C1007: =COUNTIFS(I2:I1000,"CAYm1",G2:G1000,"Ongoing")
A1008: CAYm2 | B1008: =COUNTIFS(I2:I1000,"CAYm2",G2:G1000,"Awarded") | C1008: =COUNTIFS(I2:I1000,"CAYm2",G2:G1000,"Ongoing")
A1009: CAYm3 | B1009: =COUNTIFS(I2:I1000,"CAYm3",G2:G1000,"Awarded") | C1009: =COUNTIFS(I2:I1000,"CAYm3",G2:G1000,"Ongoing")
A1010: Total | B1010: =SUM(B1007:B1009) | C1010: =SUM(C1007:C1009)

Sheet Development_Activities
A1: S. No. | B1: Department | C1: PI/Team | D1: Activity Title | E1: Type (Prototype/Patent/Transfer/Startup/Societal) | F1: TRL (if applicable) | G1: IP No. / App. No. / License Ref. | H1: Partner/Beneficiary | I1: Demo/Validation Date | J1: CAY (CAYm1/CAYm2/CAYm3) | K1: Revenue/Grant (₹) | L1: Notes/Link
A1005: Development Activities – CAY-wise Counts
A1006: Academic Year | B1006: Activities (Count) | C1006: Revenue/Grant (₹)
A1007: CAYm1 | B1007: =COUNTIF(J2:J1000,"CAYm1") | C1007: =SUMIF(J2:J1000,"CAYm1",K2:K1000)
A1008: CAYm2 | B1008: =COUNTIF(J2:J1000,"CAYm2") | C1008: =SUMIF(J2:J1000,"CAYm2",K2:K1000)
A1009: CAYm3 | B1009: =COUNTIF(J2:J1000,"CAYm3") | C1009: =SUMIF(J2:J1000,"CAYm3",K2:K1000)
A1010: Total | B1010: =SUM(B1007:B1009) | C1010: =SUM(C1007:C1009)

Sheet 6.2_Inputs
A1: Manual Marks Inputs (for sub-criteria with institute-specific rubrics)
A2: Sub-criterion | B2: Max Marks | C2: Manual Marks (Enter)
A3: 6.2.1 Academic Research | B3: 10
A4: 6.2.2 Ph.D. Student Details | B4: 5
A5: 6.2.3 Development Activities | B5: 10

Sheet R&D_6.2_Dashboard
A1: R&D 6.2 – Consolidated Dashboard (CAYm1–CAYm3)
A2: Sub-criterion | B2: Sheet(s) / Source | C2: Auto / Manual | D2: Marks (Achieved) | E2: Max Marks | F2: Notes
A3: 6.2.1 Academic Research | B3: Academic_Research + 6.2_Inputs | C3: Manual | D3: ='6.2_Inputs'!C3 | E3: 10 | F3: Enter marks per institute rubric
A4: 6.2.2 Ph.D. Student Details | B4: PhD_Students + 6.2_Inputs | C4: Manual | D4: ='6.2_Inputs'!C4 | E4: 5 | F4: Enter marks per institute rubric
A5: 6.2.3 Development Activities | B5: Development_Activities + 6.2_Inputs | C5: Manual | D5: ='6.2_Inputs'!C5 | E5: 10 | F5: Enter marks per institute rubric
A6: 6.2.4 Sponsored Research Project | B6: Projects_Details / Yearly_Summary / NBA_Marks_Dashboard | C6: Auto | D6: =NBA_Marks_Dashboard!F4 | E6: 15 | F6: Cumulative receipts thresholds
A7: 6.2.5 Consultancy Work | B7: Consultancy_Tracker / NBA_Marks_Dashboard | C7: Auto | D7: =NBA_Marks_Dashboard!F5 | E7: 15 | F7: Cumulative receipts thresholds
A8: 6.2.6 Institution Seed Money / IRG | B8: SeedMoney_Tracker / Seed_Summary | C8: Auto | D8: =Seed_Summary!B12 | E8: 5 | F8: Received (3) + Utilized (2)
A10: Grand Total | D10: =SUM(D3:D8) | E10: 60
